soupsavvy/__init__.py
soupsavvy/tags/__init__.py
soupsavvy/tags/base.py
soupsavvy/tags/components.py
soupsavvy/tags/exceptions.py
soupsavvy/tags/namespace.py
soupsorcery-0.1.5.dist-info/LICENSE
soupsorcery-0.1.5.dist-info/METADATA
soupsorcery-0.1.5.dist-info/WHEEL
soupsorcery-0.1.5.dist-info/top_level.txt
soupsorcery-0.1.5.dist-info/RECORD
