Metadata-Version: 2.1
Name: soupsorcery
Version: 0.1.5
Summary: Package for advanced web scraping with BeautifulSoup
Author: sewcio543
License: MIT License
Project-URL: source, https://github.com/sewcio543/soupsaavy
Keywords: web-scraping,html,soup,bs4,markup
Classifier: Development Status :: 1 - Planning
Classifier: Intended Audience :: Developers
Classifier: License :: OSI Approved :: MIT License
Classifier: Operating System :: OS Independent
Classifier: Programming Language :: Python :: 3
Classifier: Programming Language :: Python :: 3.9
Classifier: Programming Language :: Python :: 3.10
Classifier: Programming Language :: Python :: 3.11
Requires-Python: >=3.9
License-File: LICENSE
Requires-Dist: beautifulsoup4 ==4.12.2
Requires-Dist: lxml ==4.9.2
Provides-Extra: dev
Requires-Dist: black ==24.1.1 ; extra == 'dev'
Requires-Dist: build ==1.0.3 ; extra == 'dev'
Requires-Dist: bump2version ==1.0.1 ; extra == 'dev'
Requires-Dist: coverage ==7.2.2 ; extra == 'dev'
Requires-Dist: flake8 ==7.0.0 ; extra == 'dev'
Requires-Dist: mypy ==1.7.0 ; extra == 'dev'
Requires-Dist: pytest ==7.1.2 ; extra == 'dev'
Requires-Dist: twine ==4.0.2 ; extra == 'dev'
